{
  "name": "BLUEBERRY CUSTARD",
  "description": "Straight forward blueberry custard. Simple no frills. I will update description after I vape.",
  "id": 126817,
  "image_url": "https://storage.googleapis.com/dev-images.alltheflavors.com/uploads/recipe/imageUrl/126817/blueberry-custard-recipe-everydaydishes_com-H-740x486.jpg",
  "updated_at": "2020-12-06T20:44:24.000-05:00",
  "deleted_at": null,
  "recipe_type": 1,
  "recipe_flavors": [
    {
      "name": "Vanilla Custard",
      "flavor_id": 131,
      "millipercent": 6000,
      "vendor": "CAP"
    },
    {
      "name": "Custard",
      "flavor_id": 484,
      "millipercent": 2000,
      "vendor": "FA"
    },
    {
      "name": "Blueberry",
      "flavor_id": 1201,
      "millipercent": 5000,
      "vendor": "FW"
    },
    {
      "name": "Sweetener",
      "flavor_id": 339,
      "millipercent": 1000,
      "vendor": "TPA"
    }
  ],
  "author": "chris_walker_ffl",
  "views": "1625",
  "slug": "blueberry_custard",
  "total_flavoring": "14.0%",
  "steep_days": "21",
  "best_vg": "70%",
  "temperature": "0",
  "recipe_score": 0,
  "reviews": []
}
