{
  "name": "Xmas V1",
  "description": "This Cheery Custard vape was made on/for Interactive Mixing the Xmas month long steep mix. Excellent vape.",
  "id": 128371,
  "image_url": "https://storage.googleapis.com/dev-images.alltheflavors.com/uploads/recipe/imageUrl/128371/SmartSelect_20181121-170015_Chrome.jpg",
  "updated_at": "2020-12-06T22:03:05.000-05:00",
  "deleted_at": null,
  "recipe_type": 1,
  "recipe_flavors": [
    {
      "name": "Cerìse (cherry)",
      "flavor_id": 488,
      "millipercent": 3500,
      "vendor": "FA"
    },
    {
      "name": "Malted Milk (conc)",
      "flavor_id": 175,
      "millipercent": 2000,
      "vendor": "TPA"
    },
    {
      "name": "Super Sweet",
      "flavor_id": 2384,
      "millipercent": 500,
      "vendor": "CAP"
    },
    {
      "name": "Vanilla Bean Ice Cream",
      "flavor_id": 186,
      "millipercent": 4500,
      "vendor": "TPA"
    },
    {
      "name": "Vanilla Custard",
      "flavor_id": 131,
      "millipercent": 2250,
      "vendor": "CAP"
    },
    {
      "name": "Vanilla Swirl",
      "flavor_id": 189,
      "millipercent": 1500,
      "vendor": "TPA"
    },
    {
      "name": "White Chocolate",
      "flavor_id": 194,
      "millipercent": 3500,
      "vendor": "TPA"
    }
  ],
  "author": "Dank1",
  "views": "892",
  "slug": "xmas_v1",
  "total_flavoring": "17.75%",
  "steep_days": "30",
  "best_vg": "0%",
  "temperature": "0",
  "recipe_score": 0,
  "reviews": []
}
