{
  "name": "Foot Tapping Tango",
  "description": "G2G. 5 day steep. \r\n\r\nOriginally an attempt at Charlie Chalk Dust Head Banging Boogie. After many revisions I feel I have made something better. \r\n\r\nAlthough I haven't tried, I don't see any reason you couldnt reduce the sweetner to taste. ",
  "id": 14374,
  "image_url": "https://storage.googleapis.com/dev-images.alltheflavors.com/uploads/recipe/imageUrl/14374/1593df563ee597d5b4eb11de55a9eb56.jpg",
  "updated_at": "2020-12-08T00:48:48.000-05:00",
  "deleted_at": null,
  "recipe_type": 1,
  "recipe_flavors": [
    {
      "name": "Blueberry",
      "flavor_id": "17",
      "millipercent": 6000,
      "vendor": "CAP"
    },
    {
      "name": "Lemon Lime",
      "flavor_id": "83",
      "millipercent": 2000,
      "vendor": "CAP"
    },
    {
      "name": "Bavarian Cream",
      "flavor_id": "145",
      "millipercent": 2000,
      "vendor": "TPA"
    },
    {
      "name": "Marshmallow",
      "flavor_id": "332",
      "millipercent": 1500,
      "vendor": "TPA"
    },
    {
      "name": "Raspberry (sweet)",
      "flavor_id": "267",
      "millipercent": 2500,
      "vendor": "TPA"
    },
    {
      "name": "Golden Pineapple",
      "flavor_id": "61",
      "millipercent": 2000,
      "vendor": "CAP"
    },
    {
      "name": "Sweetener",
      "flavor_id": "339",
      "millipercent": 2000,
      "vendor": "TPA"
    }
  ],
  "author": "Bevlar",
  "views": "2369",
  "slug": "foot_tapping_tango",
  "total_flavoring": "18.0%",
  "steep_days": "5",
  "best_vg": "70%",
  "temperature": "0",
  "total_reviews": 2,
  "recipe_score": 5,
  "reviews": [
    {
      "user": "photohap",
      "score": "5",
      "text": "Very nice..  Well done."
    },
    {
      "user": "Slash",
      "score": "5",
      "text": "Not quite a clone of the original as the author states but it sure is a delicious vape, tasty as hell, smooth,sweet, delicious and chain vapeable. &#xD;\nI also made a tweaked version with 5% cap blueberry and 2% Bluberry xtra for a slightly more blue taste and mixxed with only 1% sweetener. &#xD;\n&#xD;\nWell done Bevlar for a solid and super tasty recipe. "
    }
  ]
}
