{
  "name": "Sappy",
  "description": "An overdose of vitamin C with cream. I hope you like it and give some feedback. Enjoy!",
  "id": 150369,
  "image_url": "https://storage.googleapis.com/dev-images.alltheflavors.com/uploads/recipe/imageUrl/150369/download__2_.jpg",
  "updated_at": "2020-12-08T00:50:55.000-05:00",
  "deleted_at": null,
  "recipe_type": 1,
  "recipe_flavors": [
    {
      "name": "Bavarian Cream",
      "flavor_id": 145,
      "millipercent": 1500,
      "vendor": "TPA"
    },
    {
      "name": "Cream",
      "flavor_id": 604,
      "millipercent": 800,
      "vendor": "FLV"
    },
    {
      "name": "French Vanilla Ice Cream",
      "flavor_id": 8880,
      "millipercent": 1200,
      "vendor": "VT"
    },
    {
      "name": "Juicy Orange",
      "flavor_id": 80,
      "millipercent": 1200,
      "vendor": "CAP"
    },
    {
      "name": "Meringue",
      "flavor_id": 530,
      "millipercent": 800,
      "vendor": "FA"
    },
    {
      "name": "Orange Cream",
      "flavor_id": 250,
      "millipercent": 3000,
      "vendor": "TPA"
    },
    {
      "name": "Super Sweet",
      "flavor_id": 2384,
      "millipercent": 500,
      "vendor": "CAP"
    },
    {
      "name": "Sweet Tangerine",
      "flavor_id": 123,
      "millipercent": 1000,
      "vendor": "CAP"
    },
    {
      "name": "Custard",
      "flavor_id": 4210,
      "millipercent": 1500,
      "vendor": "INW"
    },
    {
      "name": "Pudding Base",
      "flavor_id": 8948,
      "millipercent": 500,
      "vendor": "VT"
    }
  ],
  "author": "Kelgar78",
  "views": "2726",
  "slug": "sappy",
  "total_flavoring": "12.0%",
  "steep_days": "1 (SNV)",
  "best_vg": "0%",
  "temperature": "0",
  "total_reviews": 2,
  "recipe_score": 5,
  "reviews": [
    {
      "user": "kev72shell76",
      "score": "5",
      "text": "very good mix really enjoyed this and always have a bottle in the draw to grab on the go "
    },
    {
      "user": "Eirini",
      "score": "5",
      "text": "Spot on!"
    }
  ]
}
