{
    "name": "PB + Ruyan Jam V2",
    "description": "This is a VERSION 2 of Peanut Butter and Jelly recipe, blended with RY4 made from scratch\r\n\r\nMade on:\r\nhttps:\/\/www.youtube.com\/watch?v=FCbwjZlIJII",
    "id": 153770,
    "image_url": "https:\/\/storage.googleapis.com\/dev-images.alltheflavors.com\/uploads\/recipe\/imageUrl\/153770\/2222.jpg",
    "updated_at": "2020-12-10T20:01:18.000-05:00",
    "deleted_at": null,
    "recipe_type": 1,
    "recipe_flavors": [
        {
            "name": "Blackberry",
            "flavor_id": "214",
            "millipercent": 100,
            "vendor": "TPA"
        },
        {
            "name": "Blackberry Jam with Toast - SC",
            "flavor_id": "8714",
            "millipercent": 1000,
            "vendor": "RF"
        },
        {
            "name": "Custard Premium",
            "flavor_id": "9118",
            "millipercent": 2000,
            "vendor": "FA"
        },
        {
            "name": "French Pipe",
            "flavor_id": "3609",
            "millipercent": 1000,
            "vendor": "SC"
        },
        {
            "name": "Graham Cracker Clear",
            "flavor_id": "325",
            "millipercent": 4000,
            "vendor": "TPA"
        },
        {
            "name": "Dx Peanut Butter",
            "flavor_id": "288",
            "millipercent": 6000,
            "vendor": "TPA"
        },
        {
            "name": "Peanut Butter \u2013 SC",
            "flavor_id": "7529",
            "millipercent": 2500,
            "vendor": "RF"
        },
        {
            "name": "Tab Blended",
            "flavor_id": "2028",
            "millipercent": 2000,
            "vendor": "HS"
        },
        {
            "name": "Vanilla Pudding",
            "flavor_id": "4433",
            "millipercent": 1500,
            "vendor": "FLV"
        },
        {
            "name": "Super Sweet",
            "flavor_id": "2384",
            "millipercent": 250,
            "vendor": "CAP"
        }
    ],
    "author": "ENYAWREKLAW",
    "views": "2495",
    "created_at": "2019-05-31",
    "slug": "pb_ruyan_jam_v2",
    "archive_image_url": "https:\/\/allthearchives.com\/images\/153770.jpg",
    "total_flavoring": "20.35%",
    "steep_days": "10",
    "best_vg": "60%",
    "temperature": "0"
}