{
  "name": "Straw-melon pod rancher",
  "description": "Looking for a nice sweet pod recipe? Look no further folks, we've got a tasty one here!\r\n\r\nThis recipe starts with the fantastic 3-2-1 strawberry trinity, follows it up with a delicious combo of pur/fa watermelons and finishes it off with some jelly candy. \r\n\r\n\r\nThis has become the favorites of several of my close friends and its the only thing my girlfriend vapes. It would be a shame not to share it! \r\n\r\nSweeten as desired. If you enjoy menthol flavors start at about .6% ( I use a 50/50 mix of ecx ws-23 and ecx menthol solution, .3% each, with great results)\r\nFor pods I use a 50/50 vg/pg ratio and a healthy dose of nicotine. If you want to sub ohm this recipe,  you can raise the ratio and reduce the flavoring some since it wont have to rise above all that nicotine. \r\n",
  "id": 155014,
  "image_url": "https://storage.googleapis.com/dev-images.alltheflavors.com/uploads/recipe/imageUrl/155014/Strawmelon_pic.jpg",
  "updated_at": "2020-12-07T21:33:04.000-05:00",
  "deleted_at": null,
  "recipe_type": 1,
  "recipe_flavors": [
    {
      "name": "Apple Fuji",
      "flavor_id": "4886",
      "millipercent": 650,
      "vendor": "FA"
    },
    {
      "name": "Jelly Candy",
      "flavor_id": "2170",
      "millipercent": 2000,
      "vendor": "CAP"
    },
    {
      "name": "Lemon Sicily",
      "flavor_id": "524",
      "millipercent": 650,
      "vendor": "FA"
    },
    {
      "name": "Shisha Strawberry",
      "flavor_id": "1711",
      "millipercent": 3000,
      "vendor": "INW"
    },
    {
      "name": "Red Touch (strawberry)",
      "flavor_id": "421",
      "millipercent": 2000,
      "vendor": "FA"
    },
    {
      "name": "Strawberry Sweet",
      "flavor_id": "4745",
      "millipercent": 1000,
      "vendor": "JF"
    },
    {
      "name": "Super Sweet",
      "flavor_id": "7787",
      "millipercent": 500,
      "vendor": "PUR"
    },
    {
      "name": "Watermelon",
      "flavor_id": "7797",
      "millipercent": 4000,
      "vendor": "PUR"
    },
    {
      "name": "Red Summer (watermelon)",
      "flavor_id": "471",
      "millipercent": 2000,
      "vendor": "FA"
    },
    {
      "name": "Sweetener",
      "flavor_id": "1432",
      "millipercent": 500,
      "vendor": "FW"
    }
  ],
  "author": "LuckyIrish",
  "views": "1791",
  "slug": "strawmelon_pod_rancher",
  "total_flavoring": "16.3%",
  "steep_days": "3 (SNV)",
  "best_vg": "50%",
  "temperature": "0",
  "recipe_score": 0,
  "reviews": []
}
