{
    "name": "Cannibal's SHURB v3 Clone",
    "description": "v4 is available here: https:\/\/alltheflavors.com\/recipes\/22318#shurb_by_captaincannibal\r\n\r\ncaptaincannibal's SHURB clone.\r\n\r\n\"No steeping required, though a day or two will really help it out. Otherwise, shake until it turns white and your arm becomes a noodle and then enjoy the smooth, dark, enigma that is Shurb.\"\r\n\r\n\"v4 is already in the works. I've got some great suggestions and ideas for it. I already have a lot more notes written up and I'm fairly sure I figured out the cream base's percentages finally. Expect to hear more sometime next week if my new flavorings arrive.\"\r\n\r\nhttps:\/\/www.reddit.com\/r\/DIY_eJuice\/comments\/5699vs\/cannibals_shurb_v3\/?st=iu4lfo3a&sh=e8eab1f6",
    "id": 15841,
    "image_url": null,
    "updated_at": "2020-12-10T13:44:22.000-05:00",
    "deleted_at": null,
    "recipe_type": 1,
    "recipe_flavors": [
        {
            "name": "Tanger (mandarin)",
            "flavor_id": "547",
            "millipercent": 4000,
            "vendor": "FA"
        },
        {
            "name": "Vanilla Swirl",
            "flavor_id": "189",
            "millipercent": 2000,
            "vendor": "TPA"
        },
        {
            "name": "Whipped Cream",
            "flavor_id": "193",
            "millipercent": 3500,
            "vendor": "TPA"
        },
        {
            "name": "Cotton Candy",
            "flavor_id": "319",
            "millipercent": 5000,
            "vendor": "TPA"
        },
        {
            "name": "Harvest Berry",
            "flavor_id": "69",
            "millipercent": 5500,
            "vendor": "CAP"
        },
        {
            "name": "Blenderize (tutti Frutti)",
            "flavor_id": "422",
            "millipercent": 3000,
            "vendor": "FA"
        },
        {
            "name": "Key Lime",
            "flavor_id": "241",
            "millipercent": 3000,
            "vendor": "TPA"
        }
    ],
    "author": "DataNotAnecdotes",
    "views": "1794",
    "created_at": "2016-10-10",
    "slug": "cannibals_shurb_v3_clone",
    "total_flavoring": "26.0%",
    "steep_days": "2 (SNV)",
    "best_vg": "0%",
    "temperature": "0",
    "total_reviews": 1,
    "recipe_score": 0,
    "reviews": [
        {
            "user": "Mr-G",
            "score": 0,
            "text": "its ok"
        }
    ]
}