{
  "name": "Blueberry cheesecake shake",
  "description": "ODE to the developed crew! After mixing up their new strawberry cheesecake shake I was hooked instantly. I figured as good as the strawberry gummy candy was in there, blueberry gummy candy would have to be good too. Again thanks to the developed crew.",
  "id": 204158,
  "image_url": "https://storage.googleapis.com/dev-images.alltheflavors.com/uploads/recipe/imageUrl/204158/Blueberry-Milkshake-5834.jpg",
  "updated_at": "2020-12-07T07:01:49.000-05:00",
  "deleted_at": null,
  "recipe_type": 1,
  "recipe_flavors": [
    {
      "name": "Cheesecake (graham Crust)",
      "flavor_id": "152",
      "millipercent": 3000,
      "vendor": "TPA"
    },
    {
      "name": "Strawberry Cheesecake SC",
      "flavor_id": "10413",
      "millipercent": 3500,
      "vendor": "WF"
    },
    {
      "name": "Super Sweet",
      "flavor_id": "2384",
      "millipercent": 500,
      "vendor": "CAP"
    },
    {
      "name": "Vanilla Ice Cream",
      "flavor_id": "1511",
      "millipercent": 4000,
      "vendor": "LB"
    },
    {
      "name": "Yes, We Cheesecake",
      "flavor_id": "9272",
      "millipercent": 2000,
      "vendor": "INW"
    },
    {
      "name": "Blueberry Gummy Candy SC",
      "flavor_id": "10405",
      "millipercent": 2000,
      "vendor": "WF"
    },
    {
      "name": "Blueberry Jam",
      "flavor_id": "8837",
      "millipercent": 2000,
      "vendor": "VT"
    }
  ],
  "author": "Kurplop",
  "views": "794",
  "slug": "blueberry_cheesecake_shake",
  "total_flavoring": "17.0%",
  "steep_days": "3",
  "best_vg": "0%",
  "temperature": "0",
  "recipe_score": 0,
  "reviews": []
}
