{
  "name": "Blue Raz Pine Berry Fluff",
  "description": "If you're into very fruity and sweet juices, definitely make a batch of this. Amazing! \r\n\r\nThe pineapple flavor was bought on amazon. Tastes like candy pineapple more than fruit. Sub it with any pineapple. \r\nThe blue raspberry and silly rabbit are the real players here.\r\n\r\nYou won't regret it! :)",
  "id": 27623,
  "image_url": null,
  "updated_at": "2020-12-06T01:07:25.000-05:00",
  "deleted_at": null,
  "recipe_type": 1,
  "recipe_flavors": [
    {
      "name": "Blue Raspberry Cotton Candy",
      "flavor_id": 15,
      "millipercent": 5000,
      "vendor": "CAP"
    },
    {
      "name": "Pineapple (Candy)",
      "flavor_id": 6453,
      "millipercent": 3000,
      "vendor": "OOO"
    },
    {
      "name": "Strawberry (ripe)",
      "flavor_id": 271,
      "millipercent": 2000,
      "vendor": "TPA"
    },
    {
      "name": "Sweet Strawberry",
      "flavor_id": 121,
      "millipercent": 3000,
      "vendor": "CAP"
    },
    {
      "name": "Silly Rabbit Cereal",
      "flavor_id": 143,
      "millipercent": 2000,
      "vendor": "TPA"
    },
    {
      "name": "Marshmallow",
      "flavor_id": 473,
      "millipercent": 2000,
      "vendor": "FA"
    },
    {
      "name": "Marshmallow",
      "flavor_id": 332,
      "millipercent": 2000,
      "vendor": "TPA"
    },
    {
      "name": "Whipped Cream",
      "flavor_id": 193,
      "millipercent": 2000,
      "vendor": "TPA"
    }
  ],
  "author": "warmexxus",
  "views": "1104",
  "slug": "blue_raz_pine_berry_fluff",
  "total_flavoring": "21.0%",
  "steep_days": "3 (SNV)",
  "best_vg": "70%",
  "temperature": "0",
  "recipe_score": 0,
  "reviews": []
}
