{
  "name": "Goofy's Juice",
  "description": "Semi-tobacco (RY4 styled) with peanut butter and hazelnut cream.",
  "id": 66571,
  "image_url": "https://storage.googleapis.com/dev-images.alltheflavors.com/uploads/recipe/imageUrl/66571/17861809_10208341766614203_263472861198068490_n.jpg",
  "updated_at": "2020-12-08T00:49:37.000-05:00",
  "deleted_at": null,
  "recipe_type": 1,
  "recipe_flavors": [
    {
      "name": "Acetyl Pyrazine 5%",
      "flavor_id": "1709",
      "millipercent": 300,
      "vendor": "TPA"
    },
    {
      "name": "Graham Cracker Clear",
      "flavor_id": "325",
      "millipercent": 500,
      "vendor": "TPA"
    },
    {
      "name": "Hazelnut",
      "flavor_id": "1312",
      "millipercent": 1000,
      "vendor": "FW"
    },
    {
      "name": "Peanut Butter",
      "flavor_id": "291",
      "millipercent": 1000,
      "vendor": "TPA"
    },
    {
      "name": "Ry4 Double",
      "flavor_id": "379",
      "millipercent": 4000,
      "vendor": "TPA"
    }
  ],
  "author": "VladimirosStafylidis",
  "views": "7633",
  "slug": "goofys_juice",
  "total_flavoring": "6.8%",
  "steep_days": "20",
  "best_vg": "70%",
  "temperature": "0",
  "total_reviews": 6,
  "recipe_score": 5,
  "reviews": [
    {
      "user": "munhoz77",
      "score": "5",
      "text": "I love this. Always have some on My MTL. Nice balance. A really tasty Ry4 with peanut. Thanks"
    },
    {
      "user": "MixerMatt543",
      "score": "5",
      "text": "Love this juice. First recipe I followed. Very different for me!&#xD;\nConstantly got one steeping since then "
    },
    {
      "user": "nks",
      "score": "5",
      "text": "this is the best rated recipe in elr for so long time.i have mixed it so many times and in so many variations.really not much to say,for me this is the best semi tobacco recipe i have tried.the longer it steeps,the better it tastes."
    },
    {
      "user": "G8RH8R23",
      "score": "5",
      "text": "Really tasty. Mixed this up a few times now. Really well crafted"
    },
    {
      "user": "FizzChaser",
      "score": "5",
      "text": "Really enjoy this recipe. That peanut butter is subtle but really nicely balanced with the RY4."
    },
    {
      "user": "tasosetsi",
      "score": "5",
      "text": ""
    }
  ]
}
