{
  "name": "Strawberry cheesecake ",
  "description": "An approach for a strawberry cheesecake. My favourite strawberry combo used again. ",
  "id": 66584,
  "image_url": "https://storage.googleapis.com/dev-images.alltheflavors.com/uploads/recipe/imageUrl/66584/17861809_10208341766614203_263472861198068490_n.jpg",
  "updated_at": "2020-12-08T00:49:37.000-05:00",
  "deleted_at": null,
  "recipe_type": 1,
  "recipe_flavors": [
    {
      "name": "Biscuit",
      "flavor_id": 642,
      "millipercent": 800,
      "vendor": "INW"
    },
    {
      "name": "Cheesecake (graham Crust)",
      "flavor_id": 152,
      "millipercent": 1000,
      "vendor": "TPA"
    },
    {
      "name": "Graham Cracker Clear",
      "flavor_id": 325,
      "millipercent": 1000,
      "vendor": "TPA"
    },
    {
      "name": "Meringue",
      "flavor_id": 530,
      "millipercent": 1000,
      "vendor": "FA"
    },
    {
      "name": "New York Cheesecake",
      "flavor_id": 90,
      "millipercent": 4000,
      "vendor": "CAP"
    },
    {
      "name": "Strawberry (ripe)",
      "flavor_id": 271,
      "millipercent": 2000,
      "vendor": "TPA"
    },
    {
      "name": "Shisha Strawberry",
      "flavor_id": 1711,
      "millipercent": 1000,
      "vendor": "INW"
    },
    {
      "name": "Sweet Cream",
      "flavor_id": 117,
      "millipercent": 1000,
      "vendor": "CAP"
    },
    {
      "name": "Sweet Strawberry",
      "flavor_id": 121,
      "millipercent": 1000,
      "vendor": "CAP"
    }
  ],
  "author": "VladimirosStafylidis",
  "views": "2303",
  "slug": "strawberry_cheesecake",
  "total_flavoring": "12.8%",
  "steep_days": "15",
  "best_vg": "70%",
  "temperature": "0",
  "total_reviews": 1,
  "recipe_score": 5,
  "reviews": [
    {
      "user": "tasosetsi",
      "score": "5",
      "text": ""
    }
  ]
}
