{
  "name": "#DMC Challenge: Cinorange Cake ",
  "description": "Mixed up for the DMC cinnamon challenge.\r\n\r\nThis is a satisfying and rich coffee cake infused with flecks of burnt orange and cinnamon, drizzled with a thick vanilla frosting...\r\n\r\nThe FW Coffee Cake is an unsung hero in the FW stable and provides the base and body for this simple, yet complex brew. The warmth of the cinnamon in the dense coffee cake is accented by the undisputed king of cinnamons, FLV Rich cinnamon. This addition takes this luxurious cake to the next level without detracting from its essence, if used low... one drop per 30ml is plenty. \r\n\r\nThe Blood orange is a perfect and natural pairing for cinnamon and works beautifully here. It cuts the sweetness of the cake and adds sophistication. The orange is not the star of the show and is used to compliment the cinnamon, not the other way around.\r\n\r\nI opted for FLV Frosting as the finishing touch as it adds a sweet, almost fluffy, vanilla frosting. CCI has the potential to clash with the flavours here and I opted for this, more ‘natural’ icing.\r\n\r\nPs. the coffee cake contains no coffee...",
  "id": 74331,
  "image_url": "https://storage.googleapis.com/dev-images.alltheflavors.com/uploads/recipe/imageUrl/74331/FC190DF8-DB40-41B6-BC29-67E01F6AE475.jpeg",
  "updated_at": "2020-12-06T08:36:58.000-05:00",
  "deleted_at": null,
  "recipe_type": 1,
  "recipe_flavors": [
    {
      "name": "Coffee Cake",
      "flavor_id": 8476,
      "millipercent": 4000,
      "vendor": "FW"
    },
    {
      "name": "Frosting",
      "flavor_id": 4412,
      "millipercent": 3000,
      "vendor": "FLV"
    },
    {
      "name": "Rich Cinnamon",
      "flavor_id": 638,
      "millipercent": 100,
      "vendor": "FLV"
    },
    {
      "name": "Blood Orange",
      "flavor_id": 1197,
      "millipercent": 2000,
      "vendor": "FW"
    }
  ],
  "author": "RudeRudi",
  "views": "1414",
  "slug": "dmc_challenge_cinorange_cake",
  "total_flavoring": "9.1%",
  "steep_days": "5",
  "best_vg": "70%",
  "temperature": "50",
  "recipe_score": 0,
  "reviews": []
}
