{
  "name": "Hot chocolate and cream",
  "description": "I am a big fan of dark chocolate and that's the reason i use more cocoa than chocolate in this recipe.i guess that someone can adjust it to personal taste.this is a smooth chocolate and cream vape.light but yet tasty.enjoy",
  "id": 86836,
  "image_url": "https://storage.googleapis.com/dev-images.alltheflavors.com/uploads/recipe/imageUrl/86836/3e4fdd4d828c3b5481db87a9703c8839--cookies-and-cream-holiday-drinks.jpg",
  "updated_at": "2020-12-07T09:26:50.000-05:00",
  "deleted_at": null,
  "recipe_type": 1,
  "recipe_flavors": [
    {
      "name": "Cocoa",
      "flavor_id": "496",
      "millipercent": 1000,
      "vendor": "FA"
    },
    {
      "name": "Carmel (caramel)",
      "flavor_id": "503",
      "millipercent": 500,
      "vendor": "FA"
    },
    {
      "name": "Chocolate",
      "flavor_id": "489",
      "millipercent": 500,
      "vendor": "FA"
    },
    {
      "name": "Cookie",
      "flavor_id": "490",
      "millipercent": 1000,
      "vendor": "FA"
    },
    {
      "name": "Cream Fresh",
      "flavor_id": "540",
      "millipercent": 1200,
      "vendor": "FA"
    },
    {
      "name": "Creamy Hazelnut",
      "flavor_id": "1265",
      "millipercent": 800,
      "vendor": "FW"
    },
    {
      "name": "Marshmallow",
      "flavor_id": "473",
      "millipercent": 1000,
      "vendor": "FA"
    },
    {
      "name": "Milk & Honey",
      "flavor_id": "609",
      "millipercent": 1000,
      "vendor": "FLV"
    },
    {
      "name": "Shisha Vanilla",
      "flavor_id": "841",
      "millipercent": 1000,
      "vendor": "INW"
    },
    {
      "name": "Vanilla Whipped Cream",
      "flavor_id": "1",
      "millipercent": 1800,
      "vendor": "CAP"
    }
  ],
  "author": "nks",
  "views": "1072",
  "slug": "hot_chocolate_and_cream",
  "total_flavoring": "9.8%",
  "steep_days": "7",
  "best_vg": "0%",
  "temperature": "0",
  "recipe_score": 0,
  "reviews": []
}
