{
  "name": "RYForest Fire (Live Mixing 02/09)",
  "description": "Full-bodied, ashy tobacco with a slight hint of caramel and vanilla. Very dry.",
  "id": 87566,
  "image_url": null,
  "updated_at": "2020-12-07T20:32:25.000-05:00",
  "deleted_at": null,
  "recipe_type": 1,
  "recipe_flavors": [
    {
      "name": "Native Tobacco",
      "flavor_id": "4393",
      "millipercent": 1600,
      "vendor": "FLV"
    },
    {
      "name": "Connecticut Shade",
      "flavor_id": "4365",
      "millipercent": 300,
      "vendor": "FLV"
    },
    {
      "name": "RY4 Double",
      "flavor_id": "4490",
      "millipercent": 3000,
      "vendor": "JF"
    },
    {
      "name": "Smooth Vanilla",
      "flavor_id": "8570",
      "millipercent": 500,
      "vendor": "FLV"
    },
    {
      "name": "Vanilla Swirl",
      "flavor_id": "189",
      "millipercent": 500,
      "vendor": "TPA"
    },
    {
      "name": "Cinnamon Crunch",
      "flavor_id": "611",
      "millipercent": 500,
      "vendor": "FLV"
    }
  ],
  "author": "SkiddlzNinja",
  "views": "1964",
  "slug": "ryforest_fire_live_mixing_0209",
  "total_flavoring": "6.4%",
  "steep_days": "1 (SNV)",
  "best_vg": "0%",
  "temperature": "0",
  "recipe_score": 0,
  "reviews": []
}
