{
  "name": "Strap on some Berries!",
  "description": "Here is my version of ID10-T's incredible Strap-On recipe: https://alltheflavors.com/recipes/6487#strap_on_by_id10_t\r\nThe forest fruit adds a terrific touch of berry to the already great recipe.\r\nThis has become my go-to ADV that is perfect as a SNV and I thought it was time to share.\r\nI hope you enjoy!",
  "id": 95961,
  "image_url": "https://storage.googleapis.com/dev-images.alltheflavors.com/uploads/recipe/imageUrl/95961/wild_fruit_2.png",
  "updated_at": "2020-12-08T00:50:05.000-05:00",
  "deleted_at": null,
  "recipe_type": 1,
  "recipe_flavors": [
    {
      "name": "Fuji",
      "flavor_id": "506",
      "millipercent": 2000,
      "vendor": "FA"
    },
    {
      "name": "Red Touch (strawberry)",
      "flavor_id": "421",
      "millipercent": 3000,
      "vendor": "FA"
    },
    {
      "name": "Red Summer (watermelon)",
      "flavor_id": "471",
      "millipercent": 3000,
      "vendor": "FA"
    },
    {
      "name": "Forrest Mix (forest Fruit Mix)",
      "flavor_id": "453",
      "millipercent": 2000,
      "vendor": "FA"
    }
  ],
  "author": "Kothral",
  "views": "3144",
  "slug": "strap_on_some_berries",
  "total_flavoring": "10.0%",
  "steep_days": "1 (SNV)",
  "best_vg": "70%",
  "temperature": "0",
  "total_reviews": 1,
  "recipe_score": 5,
  "reviews": [
    {
      "user": "Rikkets",
      "score": "5",
      "text": ""
    }
  ]
}
