{
  "mix_id": 2115738551429,
  "mix_sid": "qzyg3udh",
  "id": 3663,
  "name": "Apfel rot süß säuerlich (Braeburn)",
  "vendor": {
    "name": "German Flavors",
    "abbreviation": "GF",
    "mix_id": 2053106938977,
    "mix_sid": "q76mv0wx"
  },
  "created_at": "2016-07-06T21:20:00.000-04:00",
  "updated_at": "2016-07-06T22:00:13.000-04:00",
  "deleted": null,
  "deleted_at": null,
  "recipe_count": 0,
  "average_millipercent": 0,
  "slug": "german-flavors-apfel-rot-suss-sauerlich-braeburn",
  "confirmed": true,
  "rejected": false,
  "vendor_url": "http://www.germanflavours.de/liquid-aromen/apfel-rot-suess-saeuerlich-braeburn-aroma.html",
  "base": null,
  "density": 1,
  "imageUrl": "",
  "description": null,
  "description_raw": null,
  "short_description": null,
  "vendor_percentage": 0,
  "vendor_description_raw": null,
  "vendor_description": null,
  "other_names": "",
  "discontinued": false,
  "tags": {}
}
