{
  "mix_id": 2080305538305,
  "mix_sid": "qjog7egx",
  "id": 7776,
  "name": "Simply Cake",
  "vendor": {
    "name": "Purilum",
    "abbreviation": "PUR",
    "mix_id": 2105523544175,
    "mix_sid": "qv9icsbz"
  },
  "created_at": "2017-05-12T14:25:16.000-04:00",
  "updated_at": "2018-12-05T12:20:16.000-05:00",
  "deleted": null,
  "deleted_at": null,
  "recipe_count": 18,
  "average_millipercent": 3806,
  "slug": "purilum-simply-cake",
  "confirmed": true,
  "rejected": false,
  "vendor_url": "https://www.nicotineriver.com/collections/purilum-flavor-concentrates/products/purilum-simply-cake",
  "base": null,
  "density": 1,
  "imageUrl": "",
  "description": null,
  "description_raw": null,
  "short_description": null,
  "vendor_percentage": 0,
  "vendor_description_raw": null,
  "vendor_description": null,
  "other_names": "",
  "discontinued": false,
  "tags": {}
}
